google_json_style/__init__.py
google_json_style/_google.py
google_json_style/_version.py
google_json_style/sanic.py
google_json_style-0.1.1.dist-info/DESCRIPTION.rst
google_json_style-0.1.1.dist-info/METADATA
google_json_style-0.1.1.dist-info/RECORD
google_json_style-0.1.1.dist-info/WHEEL
google_json_style-0.1.1.dist-info/metadata.json
google_json_style-0.1.1.dist-info/top_level.txt
