Metadata-Version: 2.0
Name: google-json-style
Version: 0.1.1
Summary: Create Google JSON Style response bodies
Home-page: https://gitlab.com/dmantis/google_json_style
Author: dmitry
Author-email: dmitry.mantis@protonmail.com
License: MIT License
Platform: UNKNOWN
